{
  "ComponentIndexes": {
    "TranslationComponent": 7
  },
  "ControlUniqueGuids": {},
  "ControlUniqueIds": {
    "566495f8-7ef6-473b-bca1-b539b41b7ee5": 46,
    "a3104c73-1fdc-4f47-acd1-bcffd25a53f9": 47,
    "App": 1,
    "BarcodeScanner": 34,
    "btnNavigateToTest": 36,
    "Button1": 20,
    "Button3": 24,
    "Button3_1": 10,
    "Button4_1": 39,
    "Button6": 42,
    "Checkbox1": 12,
    "Container1": 19,
    "Container2": 29,
    "Dropdown1": 7,
    "Gallery1": 40,
    "galleryTemplate1": 41,
    "Icon1": 15,
    "Icon2": 23,
    "Icon3": 22,
    "Icon4": 31,
    "Icon5": 5,
    "Icon6": 28,
    "Icon7": 26,
    "Icon8": 35,
    "Image1": 16,
    "Image2": 43,
    "Image3": 6,
    "Info Screen": 27,
    "Item Screen": 13,
    "Item updated screen": 25,
    "Label1": 9,
    "Label1_1": 8,
    "Label2": 14,
    "Label3": 17,
    "Label3_2": 18,
    "Label4": 30,
    "Label5": 38,
    "Label8": 32,
    "Rectangle1": 48,
    "Scan screen": 33,
    "Start Page": 4,
    "Subtitle1": 45,
    "Test Screen": 11,
    "Test web scan screen": 37,
    "Test_7F478737223C4B69": 2,
    "TextInput1": 21,
    "Title1": 44,
    "TranslationComponent": 3
  },
  "DoesTestStepsMetadataExist": true,
  "FunctionParamsInvariantScripts": {},
  "FunctionParamsInvariantScriptsOnInstances": {},
  "HeaderLastSavedDateTimeUTC": "03/01/2023 07:52:23",
  "IsLegacyComponentAllowGlobalScopeCase": false,
  "LocalConnectionIDReferences": {
    "6035816b-8ffc-4c58-b3a2-294bace33c53": "\"/providers/microsoft.powerapps/apis/shared_dynamicssmbsaas/connections/shared-dynamicssmbsa-49366530-1776-4eb0-a474-96f0993c0ff2\"",
    "d12d2ff4-7368-496c-b006-e50fd64afc64": "\"/providers/microsoft.powerapps/apis/shared_office365users/connections/4a92ed3cf19b4e738aea67aefa7e72a9\""
  },
  "LocalDatabaseReferencesAsEmpty": false,
  "LocalResourceFileNames": {
    "warehouse helper logo": "9d030933-0683-49c1-98ba-1df4e127c037.png"
  },
  "LocalResourceRootPaths": {
    "warehouse helper logo": "https://docserverpwaprodwus.blob.core.windows.net/cc0795d5-ab4c-4e6c-8525-844d97d7b1a9-1/resource/Assets0Images09d030933-0683-49c1-98ba-1df4e127c037.png?sv=2018-03-28&sr=b&sig=Ii%2BdIgz4Rc44ciPsNbN5uTZAWCKqKQqAcV5CEnVz8hM%3D&spr=https&se=2023-03-02T07%3A59%3A34Z&sp=r"
  },
  "OldLogoFileName": "vufb4v1g.jpg",
  "OrderComponentMetadata": {
    "78aad8aec73243dfa573a57ac5b247ee": 0
  },
  "OrderComponentTemplate": {
    "78aad8aec73243dfa573a57ac5b247ee": 0
  },
  "OrderDataSource": {
    "colStoredAppState": 8,
    "ComboBoxSample": 4,
    "companyInformation (v2.0)": 5,
    "CustomGallerySample": 3,
    "DropDownSample": 1,
    "items (v2.0)": 7,
    "itemsWithImage (microsoft/powerApps/beta)": 2,
    "locations (v2.0)": 6,
    "Office365-brugere": 0
  },
  "OrderGroupControls": {},
  "OrderPcfTemplate": {},
  "OrderTemplate": {},
  "OrderXMLTemplate": {
    "barcodeScanner": 9,
    "button": 4,
    "checkbox": 5,
    "dropdown": 2,
    "gallery": 10,
    "groupContainer": 6,
    "icon": 0,
    "image": 1,
    "label": 3,
    "rectangle": 8,
    "text": 7
  },
  "OverridablePropertiesEntry": {
    "566495f8-7ef6-473b-bca1-b539b41b7ee5": {},
    "a3104c73-1fdc-4f47-acd1-bcffd25a53f9": {},
    "App": {},
    "BarcodeScanner": {},
    "btnNavigateToTest": {},
    "Button1": {},
    "Button3": {},
    "Button3_1": {},
    "Button4_1": {},
    "Button6": {},
    "Checkbox1": {},
    "Container1": {},
    "Container2": {},
    "Dropdown1": {},
    "Gallery1": {},
    "galleryTemplate1": {},
    "Icon1": {},
    "Icon2": {},
    "Icon3": {},
    "Icon4": {},
    "Icon5": {},
    "Icon6": {},
    "Icon7": {},
    "Icon8": {},
    "Image1": {},
    "Image2": {},
    "Image3": {},
    "Info Screen": {},
    "Item Screen": {},
    "Item updated screen": {},
    "Label1": {},
    "Label1_1": {},
    "Label2": {},
    "Label3": {},
    "Label3_2": {},
    "Label4": {},
    "Label5": {},
    "Label8": {},
    "Rectangle1": {},
    "Scan screen": {},
    "Start Page": {},
    "Subtitle1": {},
    "Test Screen": {},
    "Test web scan screen": {},
    "Test_7F478737223C4B69": {},
    "TextInput1": {},
    "Title1": {},
    "TranslationComponent": {}
  },
  "PCFDynamicSchemaForIRRetrievalEntry": {},
  "PublishOrderIndices": {
    "566495f8-7ef6-473b-bca1-b539b41b7ee5": 0,
    "a3104c73-1fdc-4f47-acd1-bcffd25a53f9": 0,
    "App": 0,
    "BarcodeScanner": 24,
    "btnNavigateToTest": 26,
    "Button1": 17,
    "Button3": 21,
    "Button3_1": 5,
    "Button4_1": 28,
    "Button6": 31,
    "Checkbox1": 35,
    "Container1": 16,
    "Container2": 7,
    "Dropdown1": 2,
    "Gallery1": 29,
    "galleryTemplate1": 30,
    "Icon1": 12,
    "Icon2": 20,
    "Icon3": 19,
    "Icon4": 9,
    "Icon5": 0,
    "Icon6": 6,
    "Icon7": 23,
    "Icon8": 25,
    "Image1": 13,
    "Image2": 32,
    "Image3": 1,
    "Info Screen": 0,
    "Item Screen": 0,
    "Item updated screen": 0,
    "Label1": 4,
    "Label1_1": 3,
    "Label2": 11,
    "Label3": 14,
    "Label3_2": 15,
    "Label4": 8,
    "Label5": 27,
    "Label8": 10,
    "Rectangle1": 22,
    "Scan screen": 0,
    "Start Page": 0,
    "Subtitle1": 34,
    "Test Screen": 0,
    "Test web scan screen": 0,
    "Test_7F478737223C4B69": 0,
    "TextInput1": 18,
    "Title1": 33,
    "TranslationComponent": 0
  },
  "ResourcesJsonIndices": {
    "Image-SampleImage": 0,
    "Image-warehouse helper logo": 1
  },
  "RuleScreenIdWithoutScreen": {},
  "TemplateVersions": {},
  "VolatileProperties": {
    "AnalysisLoadTime": 0.2923364,
    "ControlCount": {
      "78aad8aec73243dfa573a57ac5b247ee": 1,
      "barcodeScanner": 1,
      "button": 6,
      "checkbox": 1,
      "dropdown": 1,
      "gallery": 1,
      "galleryTemplate": 1,
      "groupContainer": 2,
      "icon": 8,
      "image": 3,
      "label": 10,
      "screen": 7,
      "TestCase": 1,
      "TestSuite": 1,
      "text": 1
    },
    "DeserializationLoadTime": 1.7041209,
    "ErrorCount": 0
  },
  "WasLocalDatabaseReferencesEmpty": true
}